{
  "version": 1,
  "goalsByGame": {
    "2026-05-02|st augustine prep": [
      {
        "id": "go_mox8l3rt0hiz",
        "kind": "roster",
        "playerId": "p_modckd8lmlbz",
        "customName": "",
        "minute": null,
        "half": 1
      },
      {
        "id": "go_mox8l3rtptqm",
        "kind": "roster",
        "playerId": "p_modckd8lmlbz",
        "customName": "",
        "minute": null,
        "half": 1
      },
      {
        "id": "go_mox8l3rtp93c",
        "kind": "roster",
        "playerId": "p_modcg7j4dkv7",
        "customName": "",
        "minute": null,
        "half": 1
      },
      {
        "id": "go_mox8l3rtyje3",
        "kind": "roster",
        "playerId": "p_modcg7j4dkv7",
        "customName": "",
        "minute": null,
        "half": 1
      },
      {
        "id": "go_mox8l3rtb0tw",
        "kind": "roster",
        "playerId": "p_modcmjfbf5ef",
        "customName": "",
        "minute": null,
        "half": 1
      },
      {
        "id": "go_mox8l3rtrsjf",
        "kind": "roster",
        "playerId": "p_modcmjfbf5ef",
        "customName": "",
        "minute": null,
        "half": 1
      },
      {
        "id": "go_mox8l3rtmchc",
        "kind": "roster",
        "playerId": "p_modcpq9psnf1",
        "customName": "",
        "minute": null,
        "half": 1
      }
    ],
    "2026-05-05|opponent": [
      {
        "id": "go_mox8l3rtlxni",
        "kind": "roster",
        "playerId": "p_modcpq9psnf1",
        "customName": "",
        "minute": null,
        "half": 1
      },
      {
        "id": "go_mox8l3rt4qbd",
        "kind": "roster",
        "playerId": "p_modcpq9psnf1",
        "customName": "",
        "minute": null,
        "half": 1
      }
    ],
    "2026-05-07|badger": [
      {
        "id": "go_mox8l3rtzycd",
        "kind": "roster",
        "playerId": "p_modcpq9psnf1",
        "customName": "",
        "minute": null,
        "half": 1
      },
      {
        "id": "go_mox8l3rtnqy5",
        "kind": "roster",
        "playerId": "p_modcosrztl6c",
        "customName": "",
        "minute": null,
        "half": 1
      }
    ],
    "2026-05-07|opponent": [
      {
        "id": "go_mox8l3rtcqxm",
        "kind": "roster",
        "playerId": "p_modcpq9psnf1",
        "customName": "",
        "minute": null,
        "half": 1
      },
      {
        "id": "go_mox8l3rt6apk",
        "kind": "roster",
        "playerId": "p_modcosrztl6c",
        "customName": "",
        "minute": null,
        "half": 1
      }
    ]
  }
}